imgaugtools/__init__.py
imgaugtools/apply_augmentation.py
imgaugtools/process_images.py
imgaugtools/utils.py
imgaugtools/augmentations/__init__.py
imgaugtools/augmentations/brightness_contrast.py
imgaugtools/augmentations/color_space.py
imgaugtools/augmentations/flip.py
imgaugtools/augmentations/kernel_filters.py
imgaugtools/augmentations/random_crop.py
imgaugtools/augmentations/resize.py
imgaugtools/augmentations/rotate.py
imgaugtools-1.0.5.dist-info/METADATA
imgaugtools-1.0.5.dist-info/WHEEL
imgaugtools-1.0.5.dist-info/top_level.txt
imgaugtools-1.0.5.dist-info/RECORD
